bip322-0.2.0.dist-info/METADATA
bip322-0.2.0.dist-info/WHEEL
bip322-0.2.0.dist-info/licenses/LICENSE
bip322.libs/libgcc_s-98a1ef30.so.1
bip322/__init__.py
bip322/__init__.pyi
bip322/bip322.abi3.so
bip322/py.typed
bip322-0.2.0.dist-info/RECORD
