Metadata-Version: 2.4
Name: bip322
Version: 0.2.0
Classifier: Programming Language :: Rust
Classifier: Programming Language :: Python :: Implementation :: CPython
Classifier: Programming Language :: Python :: Implementation :: PyPy
Classifier: Operating System :: MacOS
Classifier: Operating System :: POSIX :: Linux
Classifier: Topic :: Security :: Cryptography
Classifier: License :: OSI Approved :: MIT License
License-File: LICENSE
Summary: Python ↔ Rust bridge for verifying BIP-322 Bitcoin message signatures.
Author-email: Aleksandr Kozlovskii <turosik.cy@gmail.com>
License: MIT
Requires-Python: >=3.8
Project-URL: Source, https://github.com/Turosik/bip322-py
